GortzTools/__init__.py
ScraperTools/__init__.py
gortztools/__init__.py
GortzTools-0.3.dist-info/LICENSE
GortzTools-0.3.dist-info/METADATA
GortzTools-0.3.dist-info/WHEEL
GortzTools-0.3.dist-info/top_level.txt
GortzTools-0.3.dist-info/RECORD
