Metadata-Version: 2.1
Name: GortzTools
Version: 0.3
Summary: Array to mysql tools
Home-page: https://github.com/SweGortz/gortz-tools
Author: Adrian Gortzak
Author-email: addegor95@gmail.com
License: MIT
Platform: UNKNOWN
